Metadata-Version: 1.0
Name: otumba
Version: 0.2.2
Summary: AI on Cloud Distributed Systems
Home-page: UNKNOWN
Author: Pedro Coronel Santeliz
Author-email: pelsanmexico@gmail.com
License: UNKNOWN
Platform: UNKNOWN
